_jxlpy.cpython-36m-aarch64-linux-gnu.so
jxlpy-0.9.5.dist-info/LICENSE
jxlpy-0.9.5.dist-info/METADATA
jxlpy-0.9.5.dist-info/RECORD
jxlpy-0.9.5.dist-info/top_level.txt
jxlpy-0.9.5.dist-info/WHEEL
jxlpy.libs/libbrotlienc-b60714f2.so.1
jxlpy.libs/libjxl_cms-eca087e2.so.0.10.1
jxlpy.libs/libbrotlicommon-4d1eea48.so.1.0.9
jxlpy.libs/libgcc_s-4e37474d.so.1
jxlpy.libs/libjxl_threads-4ecb6e64.so.0.10.1
jxlpy.libs/libstdc++-fd9f4683.so.6.0.28
jxlpy.libs/libjxl-a7259add.so.0.10.1
jxlpy.libs/libbrotlidec-4424ad77.so.1
jxlpy/JXLImagePlugin.py
jxlpy/__init__.py
