Metadata-Version: 2.1
Name: jxlpy
Version: 0.9.5
Summary: JPEG XL integration in Python
Home-page: http://github.com/olokelo/jxlpy
Author: oloke
Author-email: olokelo@gmail.com
License: MIT License
Classifier: Development Status :: 3 - Alpha
Classifier: Intended Audience :: Developers
Classifier: Topic :: System :: Archiving :: Compression
Classifier: Topic :: Multimedia :: Graphics
Classifier: Topic :: Multimedia :: Graphics :: Graphics Conversion
Classifier: Operating System :: OS Independent
Classifier: License :: OSI Approved :: MIT License
Classifier: Programming Language :: Cython
Classifier: Programming Language :: Python :: 3
Requires-Python: >=3.4
License-File: LICENSE
Requires-Dist: cython
Provides-Extra: pillow
Requires-Dist: Pillow; extra == "pillow"
